
main <test.lua:0,0> (12 instructions at 0000026C88446F30)
0+ params, 3 slots, 1 upvalue, 1 local, 3 constants, 1 function   
        1       [1]     VARARGPREP      0
        2       [3]     CLOSURE         0 0     ; 0000026C884470F0
        3       [1]     SETTABUP        0 0 0   ; _ENV "Add"      
        4       [5]     LOADI           0 1
        5       [6]     GETTABUP        1 0 0   ; _ENV "Add"      
        6       [6]     MOVE            2 0
        7       [6]     CALL            1 2 2   ; 1 in 1 out      
        8       [6]     SETTABUP        0 1 1   ; _ENV "b"        
        9       [7]     GETTABUP        1 0 2   ; _ENV "print"    
        10      [7]     GETTABUP        2 0 1   ; _ENV "b"        
        11      [7]     CALL            1 2 1   ; 1 in 0 out      
        12      [7]     RETURN          1 1 1   ; 0 out
constants (3) for 0000026C88446F30:
        0       S       "Add"
        1       S       "b"
        2       S       "print"
locals (1) for 0000026C88446F30:
        0       a       5       13
upvalues (1) for 0000026C88446F30:
        0       _ENV    1       0

function <test.lua:1,3> (4 instructions at 0000026C884470F0)
1 param, 2 slots, 0 upvalues, 1 local, 0 constants, 0 functions
        1       [2]     ADDI            1 0 1
        2       [2]     MMBINI          0 1 6 0 ; __add
        3       [2]     RETURN1         1
        4       [3]     RETURN0
constants (0) for 0000026C884470F0:
locals (1) for 0000026C884470F0:
        0       a       1       5
upvalues (0) for 0000026C884470F0: